odoo/addons/account_analytic_asset/README.rst
odoo/addons/account_analytic_asset/__init__.py
odoo/addons/account_analytic_asset/__manifest__.py
odoo/addons/account_analytic_asset/i18n/account_analytic_asset.pot
odoo/addons/account_analytic_asset/models/__init__.py
odoo/addons/account_analytic_asset/models/analytic_account_asset.py
odoo/addons/account_analytic_asset/readme/CONTRIBUTORS.rst
odoo/addons/account_analytic_asset/readme/DESCRIPTION.rst
odoo/addons/account_analytic_asset/static/description/icon.png
odoo/addons/account_analytic_asset/static/description/index.html
odoo/addons/account_analytic_asset/tests/__init__.py
odoo/addons/account_analytic_asset/tests/test_asset_analytic_account.py
odoo/addons/account_analytic_asset/views/account_asset_asset.xml
odoo11_addon_account_analytic_asset-11.0.1.0.0.99.dev3.dist-info/METADATA
odoo11_addon_account_analytic_asset-11.0.1.0.0.99.dev3.dist-info/WHEEL
odoo11_addon_account_analytic_asset-11.0.1.0.0.99.dev3.dist-info/top_level.txt
odoo11_addon_account_analytic_asset-11.0.1.0.0.99.dev3.dist-info/RECORD
